glj_interface/__init__.py
glj_interface/receive_amqp.py
glj_interface/send_amqp.py
glj_interface-0.0.8.dist-info/METADATA
glj_interface-0.0.8.dist-info/WHEEL
glj_interface-0.0.8.dist-info/top_level.txt
glj_interface-0.0.8.dist-info/RECORD
