Metadata-Version: 2.1
Name: glj-interface
Version: 0.0.8
Summary: Interface Communication
Home-page: UNKNOWN
Author: Jkrai44
Author-email: <jkraisinger@jlg.com>
License: UNKNOWN
Keywords: python
Platform: UNKNOWN
Classifier: Development Status :: 1 - Planning
Classifier: Intended Audience :: Developers
Classifier: Programming Language :: Python :: 3
Classifier: Operating System :: Unix
